deeprank_gnn/DataSet.py
deeprank_gnn/Graph.py
deeprank_gnn/GraphGenMP.py
deeprank_gnn/Metrics.py
deeprank_gnn/NeuralNet.py
deeprank_gnn/ResidueGraph.py
deeprank_gnn/__init__.py
deeprank_gnn/__version__.py
deeprank_gnn/community_pooling.py
deeprank_gnn/foutnet.py
deeprank_gnn/ginet.py
deeprank_gnn/sGAT.py
deeprank_gnn/tools/BSA.py
deeprank_gnn/tools/BioWrappers.py
deeprank_gnn/tools/CustomizeGraph.py
deeprank_gnn/tools/PSSM.py
deeprank_gnn/tools/__init__.py
deeprank_gnn/tools/embedding.py
deeprank_gnn/tools/hdf5_to_csv.py
deeprank_gnn/tools/pssm_3dcons_to_deeprank.py
tests/__init__.py
tests/test_biowrappers.py
tests/test_bsa.py
tests/test_community_pooling.py
tests/test_create_graph_mp.py
tests/test_dataset.py
tests/test_graph.py
tests/test_nn.py
tests/test_tools.py
tests/utils.py
DeepRank_GNN-0.1.3.dist-info/LICENSE
DeepRank_GNN-0.1.3.dist-info/METADATA
DeepRank_GNN-0.1.3.dist-info/WHEEL
DeepRank_GNN-0.1.3.dist-info/top_level.txt
DeepRank_GNN-0.1.3.dist-info/RECORD
