Metadata-Version: 2.1
Name: DeepRank-GNN
Version: 0.1.3
Summary: Graph Neural network Scoring of protein-protein conformations
Home-page: https://github.com/DeepRank/DeepRank-GNN
Author: ['Nicolas Renaud', 'Manon Reau']
Author-email: n.renaud@esciencecenter.nl
License: Apache Software License 2.0
Keywords: deeprank_gnn
Platform: UNKNOWN
Classifier: Development Status :: 2 - Pre-Alpha
Classifier: Intended Audience :: Developers
Classifier: License :: OSI Approved :: Apache Software License
Classifier: Natural Language :: English
Classifier: Programming Language :: Python :: 3.7
Classifier: Topic :: Scientific/Engineering :: Chemistry
License-File: LICENSE
Requires-Dist: numpy (>=1.13)
Requires-Dist: scipy
Requires-Dist: h5py
Requires-Dist: torch (>=1.5.0)
Requires-Dist: networkx
Requires-Dist: matplotlib
Requires-Dist: pdb2sql
Requires-Dist: sklearn
Requires-Dist: chart-studio
Requires-Dist: BioPython
Requires-Dist: python-louvain
Requires-Dist: markov-clustering
Requires-Dist: torch-sparse
Requires-Dist: torch-scatter
Requires-Dist: torch-cluster
Requires-Dist: torch-spline-conv
Requires-Dist: torch-geometric
Requires-Dist: tqdm
Requires-Dist: freesasa
Provides-Extra: dev
Requires-Dist: prospector[with_pyroma] ; extra == 'dev'
Requires-Dist: yapf ; extra == 'dev'
Requires-Dist: isort ; extra == 'dev'
Provides-Extra: doc
Requires-Dist: recommonmark ; extra == 'doc'
Requires-Dist: sphinx ; extra == 'doc'
Requires-Dist: sphinx-rtd-theme ; extra == 'doc'
Provides-Extra: test
Requires-Dist: coverage ; extra == 'test'
Requires-Dist: pycodestyle ; extra == 'test'
Requires-Dist: pytest ; extra == 'test'
Requires-Dist: pytest-cov ; extra == 'test'
Requires-Dist: pytest-runner ; extra == 'test'
Requires-Dist: coveralls ; extra == 'test'
